httpj/__init__.py
httpj/__version__.py
httpj/_api.py
httpj/_auth.py
httpj/_client.py
httpj/_config.py
httpj/_content.py
httpj/_decoders.py
httpj/_exceptions.py
httpj/_main.py
httpj/_models.py
httpj/_multipart.py
httpj/_status_codes.py
httpj/_types.py
httpj/_urlparse.py
httpj/_urls.py
httpj/_utils.py
httpj/py.typed
httpj/_transports/__init__.py
httpj/_transports/asgi.py
httpj/_transports/base.py
httpj/_transports/default.py
httpj/_transports/mock.py
httpj/_transports/wsgi.py
httpj-0.28.1.dist-info/METADATA
httpj-0.28.1.dist-info/WHEEL
httpj-0.28.1.dist-info/entry_points.txt
httpj-0.28.1.dist-info/licenses/LICENSE.md
httpj-0.28.1.dist-info/RECORD
